odoo/addons/pos_product_template/README.rst
odoo/addons/pos_product_template/__init__.py
odoo/addons/pos_product_template/__manifest__.py
odoo/addons/pos_product_template/demo/product_attribute_value.xml
odoo/addons/pos_product_template/demo/product_product.xml
odoo/addons/pos_product_template/i18n/es.po
odoo/addons/pos_product_template/i18n/fr.po
odoo/addons/pos_product_template/i18n/pos_product_template.pot
odoo/addons/pos_product_template/readme/CONTRIBUTORS.rst
odoo/addons/pos_product_template/readme/CREDITS.rst
odoo/addons/pos_product_template/readme/DESCRIPTION.rst
odoo/addons/pos_product_template/readme/ROADMAP.rst
odoo/addons/pos_product_template/readme/USAGE.rst
odoo/addons/pos_product_template/static/description/icon.png
odoo/addons/pos_product_template/static/description/index.html
odoo/addons/pos_product_template/static/src/css/ppt.css
odoo/addons/pos_product_template/static/src/img/screenshots/pos_product_template.png
odoo/addons/pos_product_template/static/src/js/ppt.js
odoo/addons/pos_product_template/static/src/xml/ppt.xml
odoo/addons/pos_product_template/view/view.xml
odoo12_addon_pos_product_template-12.0.1.0.2.dist-info/METADATA
odoo12_addon_pos_product_template-12.0.1.0.2.dist-info/WHEEL
odoo12_addon_pos_product_template-12.0.1.0.2.dist-info/top_level.txt
odoo12_addon_pos_product_template-12.0.1.0.2.dist-info/RECORD
